passwordencryption/__init__.py
passwordencryption/passwordencryption.py
passwordencryption-2024.0.1.dist-info/METADATA
passwordencryption-2024.0.1.dist-info/WHEEL
passwordencryption-2024.0.1.dist-info/licenses/LICENSE
passwordencryption-2024.0.1.dist-info/RECORD
